dsmanager/__init__.py
dsmanager/controller/__init__.py
dsmanager/controller/_async.py
dsmanager/controller/config.py
dsmanager/controller/logger.py
dsmanager/controller/save.py
dsmanager/controller/utils.py
dsmanager/datamanager/__init__.py
dsmanager/datamanager/datamanager.py
dsmanager/datamanager/datasources/__init__.py
dsmanager/datamanager/datasources/datasource.py
dsmanager/datamanager/datasources/filesource.py
dsmanager/datamanager/datasources/ftpsource.py
dsmanager/datamanager/datasources/httpsource.py
dsmanager/datamanager/datasources/kagglesource.py
dsmanager/datamanager/datasources/sfsource.py
dsmanager/datamanager/datasources/sharepointsource.py
dsmanager/datamanager/datasources/sqlsource.py
dsmanager/datamanager/datasources/sshsource.py
dsmanager/datamanager/datastorage.py
dsmanager/datamanager/utils/__init__.py
dsmanager/datamanager/utils/_column.py
dsmanager/datamanager/utils/_dataframe.py
dsmanager/datamanager/utils/_func.py
dsmanager/datamanager/utils/_pandas_object.py
dsmanager/datamanager/utils/data_pipeline.py
dsmanager/datamanager/utils/utils.py
dsmanager/model/__init__.py
dsmanager/model/model.py
dsmanager/model/modelmanager.py
dsmanager/model/utils.py
dsmanager/view/__init__.py
dsmanager-1.2.11.1.dist-info/LICENSE
dsmanager-1.2.11.1.dist-info/WHEEL
dsmanager-1.2.11.1.dist-info/METADATA
dsmanager-1.2.11.1.dist-info/RECORD
