Metadata-Version: 2.1
Name: dsmanager
Version: 1.2.11.1
Summary: Data Science tools to ease access and use of data and models
License: GPL-3.0-or-later
Author: Rayane AMROUCHE
Author-email: rayaneamrouche@gmail.com
Requires-Python: >=3.8,<4
Classifier: License :: OSI Approved :: GNU General Public License v3 or later (GPLv3+)
Classifier: Programming Language :: Python :: 3
Classifier: Programming Language :: Python :: 3.8
Classifier: Programming Language :: Python :: 3.9
Classifier: Programming Language :: Python :: 3.10
Classifier: Programming Language :: Python :: 3.11
Provides-Extra: all-sources
Provides-Extra: kaggle
Provides-Extra: models
Provides-Extra: mysql
Provides-Extra: pgsql
Provides-Extra: salesforce
Provides-Extra: sharepoint
Provides-Extra: snowflake
Requires-Dist: aiohttp (>=3.8.3,<4.0.0)
Requires-Dist: azure-common (>=1.1.28,<2.0.0) ; extra == "sharepoint" or extra == "all-sources"
Requires-Dist: azure-storage-blob (>=12.14.1,<13.0.0) ; extra == "sharepoint" or extra == "all-sources"
Requires-Dist: azure-storage-common (>=2.1.0,<3.0.0) ; extra == "sharepoint" or extra == "all-sources"
Requires-Dist: cryptography (==38.0.4)
Requires-Dist: decorator (>=5.1.1,<6.0.0)
Requires-Dist: kaggle (>=1.5.12,<2.0.0) ; extra == "kaggle" or extra == "all-sources"
Requires-Dist: llvmlite (>=0.39.1,<0.40.0)
Requires-Dist: mysqlclient (>=2.1.1,<3.0.0) ; extra == "mysql" or extra == "all-sources"
Requires-Dist: nest-asyncio (>=1.5.6,<2.0.0)
Requires-Dist: numba (>=0.56.4,<0.57.0)
Requires-Dist: numexpr (>=2.8.4,<3.0.0)
Requires-Dist: numpy (>=1.23.3,<2.0.0)
Requires-Dist: openpyxl (>=3.0.10,<4.0.0)
Requires-Dist: optuna (>=3.1.0,<4.0.0) ; extra == "models" or extra == "all-sources"
Requires-Dist: pandas (>=1.5.0,<2.0.0)
Requires-Dist: paramiko (>=2.12.0,<3.0.0)
Requires-Dist: pickle-mixin (>=1.0.2,<2.0.0)
Requires-Dist: psycopg2-binary (>=2.9.5,<3.0.0) ; extra == "pgsql" or extra == "all-sources"
Requires-Dist: python-dotenv (>=0.21.0,<0.22.0)
Requires-Dist: requests (>=2.28.1,<3.0.0)
Requires-Dist: scikit-learn (>=1.2.1,<2.0.0) ; extra == "models" or extra == "all-sources"
Requires-Dist: setuptools (>=65.6.3,<66.0.0)
Requires-Dist: shap (>=0.41.0,<0.42.0) ; extra == "models" or extra == "all-sources"
Requires-Dist: shareplum (>=0.5.1,<0.6.0) ; extra == "sharepoint" or extra == "all-sources"
Requires-Dist: simple-salesforce (>=1.12.2,<2.0.0) ; extra == "salesforce" or extra == "all-sources"
Requires-Dist: snowflake-connector-python (>=2.9.0,<3.0.0) ; extra == "snowflake" or extra == "all-sources"
Requires-Dist: snowflake-sqlalchemy (>=1.4.4,<2.0.0) ; extra == "snowflake" or extra == "all-sources"
Requires-Dist: sqlalchemy[asyncio] (>=1.4.46,<2.0.0)
Requires-Dist: tqdm (>=4.64.1,<5.0.0)
Requires-Dist: xlrd (>=2.0.1,<3.0.0)
